Metadata-Version: 2.1
Name: pyamjdlool
Version: 0.1
Summary: my name 
Author: Amjad Almflihy
License-File: License.txt
